hdt_sampling-0.2.0.dist-info/METADATA
hdt_sampling-0.2.0.dist-info/WHEEL
hdt_sampling-0.2.0.dist-info/licenses/LICENSE
hdt_sampling/__init__.py
hdt_sampling/__init__.pyi
hdt_sampling/hdt_sampling.pypy39-pp73-s390x-linux-gnu.so
hdt_sampling/py.typed
hdt_sampling-0.2.0.dist-info/RECORD
