Metadata-Version: 2.4
Name: hdt_sampling
Version: 0.2.0
Classifier: Programming Language :: Rust
Classifier: Programming Language :: Python :: Implementation :: CPython
Classifier: Programming Language :: Python :: Implementation :: PyPy
Requires-Dist: ipykernel>=6.29.5 ; extra == 'dev'
Requires-Dist: matplotlib>=3.7.5 ; extra == 'dev'
Requires-Dist: numpy>=1.24.4 ; extra == 'dev'
Requires-Dist: scipy>=1.10.1 ; extra == 'dev'
Provides-Extra: dev
License-File: LICENSE
Summary: Fast Hierarchical Dart Throwing sampling implemented in Rust for Python.
Requires-Python: >=3.8
